jobs_detector/__init__.py
jobs_detector/exceptions.py
jobs_detector/main.py
jobs_detector/models.py
jobs_detector/settings.py
rmotr_b9_c1_g5_jobs_detector-0.0.3.dist-info/DESCRIPTION.rst
rmotr_b9_c1_g5_jobs_detector-0.0.3.dist-info/METADATA
rmotr_b9_c1_g5_jobs_detector-0.0.3.dist-info/RECORD
rmotr_b9_c1_g5_jobs_detector-0.0.3.dist-info/WHEEL
rmotr_b9_c1_g5_jobs_detector-0.0.3.dist-info/entry_points.txt
rmotr_b9_c1_g5_jobs_detector-0.0.3.dist-info/metadata.json
rmotr_b9_c1_g5_jobs_detector-0.0.3.dist-info/top_level.txt
