Metadata-Version: 2.0
Name: rmotr-b9-c1-g5-jobs-detector
Version: 0.0.3
Summary: rmotr.com Group Project | Jobs Detector
Home-page: https://github.com/jangeador/pyp-w3-gw-jobs-detector
Author: rmotr.com
Author-email: jangeador@gmail.com
License: CC BY-SA 4.0 License
Platform: UNKNOWN
Requires-Dist: bs4
Requires-Dist: click
Requires-Dist: requests-cache
